swarmauri_tokens_introspection/IntrospectionTokenService.py
swarmauri_tokens_introspection/__init__.py
swarmauri_tokens_introspection-0.3.0.dev4.dist-info/LICENSE
swarmauri_tokens_introspection-0.3.0.dev4.dist-info/METADATA
swarmauri_tokens_introspection-0.3.0.dev4.dist-info/WHEEL
swarmauri_tokens_introspection-0.3.0.dev4.dist-info/entry_points.txt
swarmauri_tokens_introspection-0.3.0.dev4.dist-info/RECORD
