Metadata-Version: 2.3
Name: swarmauri_tokens_introspection
Version: 0.3.0.dev4
Summary: OAuth 2.0 Token Introspection service for Swarmauri
License: Apache-2.0
Author: Swarmauri
Author-email: opensource@swarmauri.com
Requires-Python: >=3.10,<3.13
Classifier: License :: OSI Approved :: Apache Software License
Classifier: Natural Language :: English
Classifier: Programming Language :: Python :: 3.10
Classifier: Programming Language :: Python :: 3.11
Classifier: Programming Language :: Python :: 3.12
Classifier: Programming Language :: Python :: 3.13
Classifier: Development Status :: 3 - Alpha
Classifier: Topic :: Internet :: WWW/HTTP
Classifier: Intended Audience :: Developers
Provides-Extra: jwks
Provides-Extra: redis-cache
Requires-Dist: httpx
Requires-Dist: jwcrypto (>=1.5) ; extra == "jwks"
Requires-Dist: redis (>=5.0) ; extra == "redis-cache"
Requires-Dist: swarmauri_base
Requires-Dist: swarmauri_core
